chatbotlib/__init__.py
chatbotlib/chatbotlib.py
python_chatbotlib-1.0.1.dist-info/METADATA
python_chatbotlib-1.0.1.dist-info/WHEEL
python_chatbotlib-1.0.1.dist-info/entry_points.txt
python_chatbotlib-1.0.1.dist-info/top_level.txt
python_chatbotlib-1.0.1.dist-info/RECORD
