Metadata-Version: 2.4
Name: python-chatbotlib
Version: 1.0.1
Requires-Dist: requests>=2.32.3
Requires-Dist: beautifulsoup4>=4.12.3
Dynamic: requires-dist
